quantsnet/__init__.py
quantsnet/bs.py
quants_net-0.0.1.dist-info/METADATA
quants_net-0.0.1.dist-info/WHEEL
quants_net-0.0.1.dist-info/top_level.txt
quants_net-0.0.1.dist-info/RECORD
